odoo/addons/partner_contact_address_default/README.rst
odoo/addons/partner_contact_address_default/__init__.py
odoo/addons/partner_contact_address_default/__manifest__.py
odoo/addons/partner_contact_address_default/i18n/es.po
odoo/addons/partner_contact_address_default/i18n/fr.po
odoo/addons/partner_contact_address_default/i18n/fr_FR.po
odoo/addons/partner_contact_address_default/i18n/it.po
odoo/addons/partner_contact_address_default/i18n/partner_contact_address_default.pot
odoo/addons/partner_contact_address_default/i18n/pt.po
odoo/addons/partner_contact_address_default/models/__init__.py
odoo/addons/partner_contact_address_default/models/res_partner.py
odoo/addons/partner_contact_address_default/readme/CONTRIBUTORS.md
odoo/addons/partner_contact_address_default/readme/DESCRIPTION.md
odoo/addons/partner_contact_address_default/readme/USAGE.md
odoo/addons/partner_contact_address_default/static/description/icon.png
odoo/addons/partner_contact_address_default/static/description/index.html
odoo/addons/partner_contact_address_default/tests/__init__.py
odoo/addons/partner_contact_address_default/tests/test_partner_contact_address_default.py
odoo/addons/partner_contact_address_default/views/res_partner_views.xml
odoo_addon_partner_contact_address_default-19.0.1.0.0.5.dist-info/METADATA
odoo_addon_partner_contact_address_default-19.0.1.0.0.5.dist-info/WHEEL
odoo_addon_partner_contact_address_default-19.0.1.0.0.5.dist-info/top_level.txt
odoo_addon_partner_contact_address_default-19.0.1.0.0.5.dist-info/RECORD
