Metadata-Version: 2.1
Name: odoo-addon-partner_contact_address_default
Version: 19.0.1.0.0.5
Requires-Dist: odoo==19.0.*
Summary: Set a default delivery address, invoice address and contact for contacts
Home-page: https://github.com/OCA/partner-contact
License: AGPL-3
Author: Tecnativa, Odoo Community Association (OCA)
Author-email: support@odoo-community.org
Classifier: Programming Language :: Python
Classifier: Framework :: Odoo
Classifier: Framework :: Odoo :: 19.0
Classifier: License :: OSI Approved :: GNU Affero General Public License v3
Classifier: Development Status :: 4 - Beta
